django_payhero-0.1.1.dist-info/licenses/LICENSE
payhero_django/__init__.py
payhero_django/admin.py
payhero_django/api.py
payhero_django/apps.py
payhero_django/exceptions.py
payhero_django/models.py
payhero_django/urls.py
payhero_django/utils.py
payhero_django/views.py
django_payhero-0.1.1.dist-info/METADATA
django_payhero-0.1.1.dist-info/WHEEL
django_payhero-0.1.1.dist-info/top_level.txt
django_payhero-0.1.1.dist-info/RECORD
